<?xml version="1.0" encoding="utf-8"?>
<chart xmlns:dxp="http://schemas.google.com/analytics/2009" xmlns:a="http://www.w3.org/2005/Atom">
  <series>
    <value xid="0">18 мая</value>
    <value xid="1">19 мая</value>
    <value xid="2">20 мая</value>
    <value xid="3">21 мая</value>
    <value xid="4">22 мая</value>
    <value xid="5">23 мая</value>
    <value xid="6">24 мая</value>
    <value xid="7">25 мая</value>
    <value xid="8">26 мая</value>
    <value xid="9">27 мая</value>
    <value xid="10">28 мая</value>
    <value xid="11">29 мая</value>
    <value xid="12">30 мая</value>
    <value xid="13">31 мая</value>
    <value xid="14">01 июня</value>
    <value xid="15">02 июня</value>
    <value xid="16">03 июня</value>
    <value xid="17">04 июня</value>
    <value xid="18">05 июня</value>
    <value xid="19">06 июня</value>
    <value xid="20">07 июня</value>
    <value xid="21">08 июня</value>
    <value xid="22">09 июня</value>
    <value xid="23">10 июня</value>
    <value xid="24">11 июня</value>
    <value xid="25">12 июня</value>
    <value xid="26">13 июня</value>
    <value xid="27">14 июня</value>
    <value xid="28">15 июня</value>
    <value xid="29">16 июня</value>
    <value xid="30">17 июня</value>
    <value xid="31">18 июня</value>
    <value xid="32">19 июня</value>
    <value xid="33">20 июня</value>
    <value xid="34">21 июня</value>
    <value xid="35">22 июня</value>
    <value xid="36">23 июня</value>
    <value xid="37">24 июня</value>
    <value xid="38">25 июня</value>
    <value xid="39">26 июня</value>
    <value xid="40">27 июня</value>
    <value xid="41">28 июня</value>
    <value xid="42">29 июня</value>
    <value xid="43">30 июня</value>
    <value xid="44">01 июля</value>
    <value xid="45">02 июля</value>
    <value xid="46">03 июля</value>
    <value xid="47">04 июля</value>
    <value xid="48">05 июля</value>
    <value xid="49">06 июля</value>
    <value xid="50">07 июля</value>
    <value xid="51">08 июля</value>
    <value xid="52">09 июля</value>
    <value xid="53">10 июля</value>
    <value xid="54">11 июля</value>
    <value xid="55">12 июля</value>
    <value xid="56">13 июля</value>
    <value xid="57">14 июля</value>
    <value xid="58">15 июля</value>
    <value xid="59">16 июля</value>
    <value xid="60">17 июля</value>
    <value xid="61">18 июля</value>
    <value xid="62">19 июля</value>
    <value xid="63">20 июля</value>
    <value xid="64">21 июля</value>
    <value xid="65">22 июля</value>
    <value xid="66">23 июля</value>
    <value xid="67">24 июля</value>
    <value xid="68">25 июля</value>
    <value xid="69">26 июля</value>
    <value xid="70">27 июля</value>
    <value xid="71">28 июля</value>
    <value xid="72">29 июля</value>
    <value xid="73">30 июля</value>
    <value xid="74">31 июля</value>
    <value xid="75">01 августа</value>
    <value xid="76">02 августа</value>
    <value xid="77">03 августа</value>
    <value xid="78">04 августа</value>
    <value xid="79">05 августа</value>
    <value xid="80">06 августа</value>
    <value xid="81">07 августа</value>
    <value xid="82">08 августа</value>
    <value xid="83">09 августа</value>
    <value xid="84">10 августа</value>
    <value xid="85">11 августа</value>
    <value xid="86">12 августа</value>
    <value xid="87">13 августа</value>
    <value xid="88">14 августа</value>
    <value xid="89">15 августа</value>
  </series>
  <graphs>
    <graph gid="pageviews">
      <value xid="0">33138</value>
      <value xid="1">30823</value>
      <value xid="2">27792</value>
      <value xid="3">32249</value>
      <value xid="4">35451</value>
      <value xid="5">33826</value>
      <value xid="6">35603</value>
      <value xid="7">33276</value>
      <value xid="8">33017</value>
      <value xid="9">30258</value>
      <value xid="10">33109</value>
      <value xid="11">31091</value>
      <value xid="12">35677</value>
      <value xid="13">34786</value>
      <value xid="14">31610</value>
      <value xid="15">31279</value>
      <value xid="16">33216</value>
      <value xid="17">35198</value>
      <value xid="18">32226</value>
      <value xid="19">31948</value>
      <value xid="20">34177</value>
      <value xid="21">34210</value>
      <value xid="22">33154</value>
      <value xid="23">31437</value>
      <value xid="24">32208</value>
      <value xid="25">33574</value>
      <value xid="26">35434</value>
      <value xid="27">38325</value>
      <value xid="28">34982</value>
      <value xid="29">30255</value>
      <value xid="30">29451</value>
      <value xid="31">33625</value>
      <value xid="32">36724</value>
      <value xid="33">36061</value>
      <value xid="34">36365</value>
      <value xid="35">32944</value>
      <value xid="36">31657</value>
      <value xid="37">30514</value>
      <value xid="38">31651</value>
      <value xid="39">35236</value>
      <value xid="40">33256</value>
      <value xid="41">34342</value>
      <value xid="42">31645</value>
      <value xid="43">31022</value>
      <value xid="44">27989</value>
      <value xid="45">32854</value>
      <value xid="46">34119</value>
      <value xid="47">31750</value>
      <value xid="48">26890</value>
      <value xid="49">25889</value>
      <value xid="50">25127</value>
      <value xid="51">22207</value>
      <value xid="52">23899</value>
      <value xid="53">26481</value>
      <value xid="54">25305</value>
      <value xid="55">25833</value>
      <value xid="56">26725</value>
      <value xid="57">22720</value>
      <value xid="58">22432</value>
      <value xid="59">24824</value>
      <value xid="60">16926</value>
      <value xid="61">24255</value>
      <value xid="62">24498</value>
      <value xid="63">26802</value>
      <value xid="64">23157</value>
      <value xid="65">21907</value>
      <value xid="66">26111</value>
      <value xid="67">21485</value>
      <value xid="68">26266</value>
      <value xid="69">25380</value>
      <value xid="70">24536</value>
      <value xid="71">21959</value>
      <value xid="72">20829</value>
      <value xid="73">21592</value>
      <value xid="74">23173</value>
      <value xid="75">21335</value>
      <value xid="76">22749</value>
      <value xid="77">23298</value>
      <value xid="78">22410</value>
      <value xid="79">19757</value>
      <value xid="80">21480</value>
      <value xid="81">22671</value>
      <value xid="82">24999</value>
      <value xid="83">24272</value>
      <value xid="84">23205</value>
      <value xid="85">22821</value>
      <value xid="86">20116</value>
      <value xid="87">23327</value>
      <value xid="88">23452</value>
      <value xid="89">24551</value>
    </graph>
    <graph gid="visits">
      <value xid="0">7565</value>
      <value xid="1">7202</value>
      <value xid="2">7001</value>
      <value xid="3">7296</value>
      <value xid="4">7751</value>
      <value xid="5">7236</value>
      <value xid="6">7595</value>
      <value xid="7">7107</value>
      <value xid="8">7304</value>
      <value xid="9">6867</value>
      <value xid="10">7256</value>
      <value xid="11">6967</value>
      <value xid="12">7875</value>
      <value xid="13">7791</value>
      <value xid="14">7105</value>
      <value xid="15">7285</value>
      <value xid="16">7477</value>
      <value xid="17">7897</value>
      <value xid="18">7711</value>
      <value xid="19">7804</value>
      <value xid="20">8013</value>
      <value xid="21">8507</value>
      <value xid="22">8316</value>
      <value xid="23">7428</value>
      <value xid="24">7704</value>
      <value xid="25">7983</value>
      <value xid="26">8052</value>
      <value xid="27">8687</value>
      <value xid="28">7869</value>
      <value xid="29">7369</value>
      <value xid="30">6847</value>
      <value xid="31">7767</value>
      <value xid="32">8053</value>
      <value xid="33">7747</value>
      <value xid="34">7915</value>
      <value xid="35">7399</value>
      <value xid="36">7201</value>
      <value xid="37">7204</value>
      <value xid="38">7370</value>
      <value xid="39">7759</value>
      <value xid="40">7581</value>
      <value xid="41">7511</value>
      <value xid="42">7508</value>
      <value xid="43">7227</value>
      <value xid="44">7187</value>
      <value xid="45">7899</value>
      <value xid="46">7913</value>
      <value xid="47">7095</value>
      <value xid="48">5864</value>
      <value xid="49">5759</value>
      <value xid="50">5225</value>
      <value xid="51">5006</value>
      <value xid="52">5497</value>
      <value xid="53">6566</value>
      <value xid="54">5764</value>
      <value xid="55">6197</value>
      <value xid="56">5901</value>
      <value xid="57">5119</value>
      <value xid="58">5069</value>
      <value xid="59">5403</value>
      <value xid="60">3908</value>
      <value xid="61">5257</value>
      <value xid="62">5217</value>
      <value xid="63">5610</value>
      <value xid="64">4919</value>
      <value xid="65">4968</value>
      <value xid="66">5239</value>
      <value xid="67">4661</value>
      <value xid="68">5169</value>
      <value xid="69">5226</value>
      <value xid="70">5528</value>
      <value xid="71">5031</value>
      <value xid="72">4825</value>
      <value xid="73">5162</value>
      <value xid="74">5225</value>
      <value xid="75">5025</value>
      <value xid="76">5212</value>
      <value xid="77">5522</value>
      <value xid="78">4872</value>
      <value xid="79">4744</value>
      <value xid="80">5097</value>
      <value xid="81">5053</value>
      <value xid="82">5227</value>
      <value xid="83">5305</value>
      <value xid="84">5288</value>
      <value xid="85">4983</value>
      <value xid="86">4763</value>
      <value xid="87">5003</value>
      <value xid="88">5199</value>
      <value xid="89">5207</value>
    </graph>
  </graphs>
</chart>
