{
"$total":[299406,269973],
"48 капель":[98,83],
"911":[241,218],
"Абрикосовая маргарита с перцем":[41,35],
"Абрикосово-апельсиновый лимонад в кувшине":[48,45],
"Абсент без разрешения":[357,314],
"Абсент в фонтане":[99,91],
"Абсент и ананас":[380,317],
"Абсент с энергетиком":[177,161],
"Абсент сауэр":[131,115],
"Авиация":[408,374],
"Адвокат Дьявола":[183,172],
"Ай кью":[183,162],
"Айриш крим со льдом":[87,77],
"Александр":[572,509],
"Александра":[121,114],
"Алко-шашки":[263,233],
"Аллилуйя":[196,186],
"Алые паруса":[296,258],
"Амба":[74,73],
"Американо":[851,755],
"Амиго":[441,384],
"Ананасово-гранатовый фреш":[214,195],
"Ананасово-яблочный милкшейк":[165,140],
"Ананасовый виски":[246,211],
"Ананасовый детокс":[238,219],
"Ангельская сиська":[125,109],
"Ангельские сиськи":[896,827],
"Английская девственница":[272,251],
"Английский":[72,67],
"Английский завтрак":[75,72],
"Антифриз в огурце":[296,268],
"Антоний Пий":[42,38],
"Антонио":[84,77],
"Апельсиново-манговая самбука":[102,96],
"Апельсиновый чейзер":[170,147],
"Апри кот":[186,164],
"Аравика":[205,194],
"Арбузная маргарита":[47,44],
"Арбузный коблер 317":[110,91],
"Арбузный лимонад":[109,95],
"Арбузный слинг":[153,144],
"Арбузный тай слинг":[44,40],
"Арбузный эль":[131,112],
"Арно":[128,115],
"Асаи сауэр":[119,112],
"Ацтек":[175,151],
"Б-52":[5729,5018],
"Баба Таня":[136,118],
"Бабушкин сад":[77,73],
"Бабье лето":[77,73],
"Баварская груша":[40,37],
"Бадминтон":[135,123],
"Базил смэш":[249,235],
"Базилично-ежевичный слинг":[51,47],
"Бакарди симфони":[76,70],
"Бали дрим":[97,85],
"Бальбин":[83,79],
"Бамбу 2":[44,43],
"Банановая самбука":[150,137],
"Банши":[119,109],
"Барбадоска":[123,116],
"Барбара ти панч":[72,70],
"Барбарис физ":[91,86],
"Барби":[139,121],
"Баттер скотч":[92,83],
"Баунти мартини":[256,221],
"Бахус":[46,39],
"Бахус пати":[63,61],
"Белая леди":[706,616],
"Белая сангрия в кувшине":[95,86],
"Белая сангрия в пунше":[51,46],
"Беллини":[672,627],
"Белый глинтвейн":[54,45],
"Белый кубинец":[103,96],
"Белый лимонный глинтвейн":[58,55],
"Белый мексиканец":[222,210],
"Белый русский":[6865,6267],
"Березовый кулер":[105,93],
"БерриМиАп":[75,69],
"Бессонница":[60,58],
"Би-Блэк":[328,299],
"Бир берри рояль":[54,50],
"Биттер мелон":[147,129],
"Блекбери шот":[214,189],
"Блинк-блинк":[40,39],
"Блоу джоб":[259,237],
"Блэк вуд":[41,39],
"Блэк саббат":[148,133],
"Бог Марс":[102,94],
"Богемный холодный чай":[132,121],
"Бодрячок":[129,120],
"Бока чика":[101,94],
"Большой яблочный мартини":[47,43],
"Борец":[236,217],
"Борзая":[102,95],
"Бородинский":[59,56],
"Бостонский чай":[379,345],
"Боулинг в ТУ-154":[1120,964],
"Бочонок с медом":[74,68],
"Боярский":[2448,2183],
"Бразильский лимонад":[104,103],
"Бренди Александр":[410,373],
"Бренди бак":[56,52],
"Бренди круста":[55,53],
"Бренди сауэр":[89,86],
"Брис оф Бали":[49,46],
"БричМула":[58,48],
"Бронкс":[378,347],
"Брусничный с апельсином":[225,198],
"Бубен шотов":[143,137],
"Бубль-гум":[385,351],
"Буз физ":[49,45],
"Бумбокс":[204,186],
"Бурбон кола":[169,146],
"Бурбон на апельсине":[46,40],
"Бурбон на бруснике":[49,49],
"Бурбон на вишне":[91,79],
"Бурбон на клубнике":[47,43],
"Бурбон на кураге":[41,33],
"Бурбон на малине":[44,39],
"Бурбон на облепихе":[47,42],
"Бухарест":[288,248],
"Быстрый ванильный шот":[58,54],
"Бьянко апельсин":[297,264],
"Бьянко биттер лемон":[139,128],
"Бьянко бриз":[205,188],
"Бьянко ванильное яблоко":[63,60],
"Бьянко лемон айс":[351,307],
"Бьянко санрайз":[466,413],
"Бьянко тоник":[595,521],
"В ее глазах":[74,68],
"Валенсианская вода в кувшине":[47,41],
"Валенсия":[189,179],
"Ванила айс":[102,96],
"Ванила кик":[51,48],
"Ванила коллинз":[42,40],
"Ванильный бриз":[98,93],
"Ванильный шот":[117,107],
"Ванна пузырьков мартини":[85,79],
"Варекай":[44,40],
"Великая стена шутер":[51,45],
"Вельветовый дайкири":[100,95],
"Веспер":[563,503],
"Вечерний грог":[58,55],
"Вечнозеленый физ":[115,108],
"Взрыв мозга":[969,851],
"Виноградный Мохито":[43,38],
"Виноградный коблер 317":[66,62],
"Виноградный слинг":[79,75],
"Виолетта":[103,96],
"Виски Тай":[78,73],
"Виски абрикос грейпфрут":[168,158],
"Виски кола":[1735,1587],
"Виски мармеладный драм":[64,59],
"Виски он зе рокс":[334,298],
"Виски персиковая мята":[65,61],
"Виски персиковый чай":[239,209],
"Виски с вишней":[433,388],
"Виски сауэр":[1900,1746],
"Виски сауэр Моджо":[140,129],
"Виски физ":[105,99],
"Виски яблочный сок":[517,475],
"Витаминный":[78,74],
"Витаминный лимонад в кувшине":[128,113],
"Вишневая самбука":[259,237],
"Вишнево-пряничный смузи":[188,175],
"Вишневое пиво":[132,116],
"Вишневый ликер и грейпфрут":[153,138],
"Вишневый сауэр":[114,104],
"Вишня и вишня":[38,33],
"Водевиль":[70,69],
"Водка биттер мед":[98,90],
"Водка ванильная клюква":[64,61],
"Водка ванильное яблоко":[41,35],
"Водка гранатовый сок":[479,429],
"Водка грушевая спрайт":[39,36],
"Водка мандарин":[182,170],
"Водка мартини":[2838,2592],
"Водка мятный чай":[115,111],
"Водка он зе рокс":[264,244],
"Водка смэш":[268,237],
"Водка спрайт":[1126,1017],
"Водка тоник":[396,365],
"Водка цитрон тоник":[46,39],
"Водка энергетик":[700,634],
"Водка энергетик мини":[665,595],
"Вокруг света":[60,55],
"Волшебная вода":[284,260],
"Ворошиловский стрелок":[106,98],
"Восток встречает Запад":[70,63],
"Восточное чаепитие":[40,39],
"Восточный мед":[50,43],
"Восточный экспресс":[81,74],
"Все падают":[257,230],
"Ву-ву":[319,284],
"Выше облаков":[81,70],
"Галилео":[142,127],
"Гальяно хот шот":[193,173],
"Гарибальди":[577,525],
"Гейша мартини":[86,78],
"Генриэтта Хадсон":[42,40],
"Гимлет":[257,230],
"Гимлет 2":[182,167],
"Глинтвейн":[205,172],
"Глория":[105,92],
"Глубинная секс-бомба":[304,271],
"Гней Помпей Великий":[54,49],
"Гоголь-моголь":[231,215],
"Голден Рико":[72,57],
"Голден физ":[145,133],
"Голдинез":[59,48],
"Голландская храбрость":[45,40],
"Голубая лагуна":[8569,7560],
"Голубая луна":[459,409],
"Голубичный коллинз":[70,64],
"Голубое искушение":[302,262],
"Гораций":[61,58],
"Горькая пилюля":[202,175],
"Горячее золото":[237,220],
"Горячее золото во френч-прессе":[52,49],
"Горячий апельсин":[124,118],
"Горячий и острый":[38,38],
"Горячий ром с маслом":[60,57],
"Горячий ромовый пунш":[74,71],
"Горячий тодди":[134,126],
"Горящий Генри":[239,223],
"Горящий Феррари":[491,454],
"Гранатовая маргарита":[82,76],
"Гранатово-грейпфрутовый фреш":[94,87],
"Гранатовый тини":[221,204],
"Гранд Сазерак":[88,78],
"Гранд мимоза":[123,117],
"Гранд'О":[58,55],
"Граф":[134,125],
"Грейпфрут сплеш":[62,56],
"Грейпфрутовый виски сауэр":[70,66],
"Грейпфрутовый компот в кувшине":[163,149],
"Грейпфрутовый лимонад в кувшине":[131,117],
"Гремучая змея":[150,134],
"Греческая смоковница":[40,31],
"Грин тини":[114,100],
"Грин хоуп":[107,97],
"Грог":[401,370],
"Грушевый бриз":[49,44],
"Грушевый милкшейк":[70,65],
"Грушевый шот":[42,39],
"Гуд тайм герл":[58,55],
"Дайкири":[6988,6232],
"Дайкири Гарри":[54,51],
"Дайкири Майя":[49,43],
"Дайкири гранатовый":[308,279],
"Дайкири малиновый":[109,104],
"Дайкири с грейпфрутовым соком":[244,227],
"Дайкири с мёдом и базиликом":[82,74],
"Дальневосточный физ":[45,42],
"Дарк сайд":[121,117],
"Двойное удовольствие":[79,73],
"Дебютант":[86,78],
"День напролет":[109,101],
"Деревянный Джек":[108,99],
"Джайв Смэш":[43,38],
"Джамбо":[75,68],
"Джек Роуз":[202,182],
"Джекки":[48,46],
"Джимми-Джимми":[38,35],
"Джин Бутик":[128,109],
"Джин биттер лемон":[265,226],
"Джин гарден":[165,158],
"Джин и клюква":[337,299],
"Джин мул":[114,107],
"Джин на красной смородине":[64,60],
"Джин на малине":[181,165],
"Джин на черной смородине":[114,102],
"Джин персиковый чай":[50,48],
"Джин тоник":[2350,2093],
"Джин тоник с огурцом":[290,270],
"Джин физ":[642,588],
"Джу джулеп":[57,55],
"Дикая земля":[85,77],
"Диксиленд смэш":[72,64],
"Диоскорид":[42,41],
"Добрый кокос":[71,64],
"Долорес парк свизл":[46,43],
"Домашний Лебовски":[304,272],
"Домашний виноградный Мохито":[47,43],
"Домашний классический Мохито":[471,444],
"Домашний клубничный Мохито":[59,50],
"Домашний мандариновый Мохито":[41,37],
"Домашний мармелад":[61,58],
"Домашний папин двойной":[77,69],
"Домашний слинг":[264,239],
"Домашний фэшнд":[206,188],
"Дочь Боярского":[567,509],
"Драй мартини":[1537,1382],
"Древнегреческий":[281,257],
"Дрим дайкири меренги":[63,57],
"Дрим шот":[92,88],
"Дух '57":[60,57],
"Душевный пунш":[79,71],
"Дымный":[116,112],
"Дымный флип":[57,51],
"Дымный шотландец":[76,70],
"Дымный яблочный пирог":[68,62],
"Дынно-базиличный смузи":[88,81],
"Дынный Беллини":[59,56],
"Дьюк тюлип":[38,32],
"Дьябло":[262,237],
"Е-сенча-Л":[70,65],
"Ежевичный коблер":[78,62],
"Ежевичный милкшейк":[126,115],
"Жидкий чизкейк":[119,104],
"Жизнь прекрасна":[85,78],
"Завтрак":[285,260],
"Завтрак Джокера":[222,199],
"Завтрак с Дали":[96,88],
"Запеченный смузи":[309,276],
"Запретный плод":[94,80],
"Захарофф форест":[77,70],
"Зеленая терраса":[44,44],
"Зеленая фея":[1833,1690],
"Зеленая фея пунш":[155,144],
"Зеленый луч":[145,132],
"Земполе":[79,70],
"Зима":[57,55],
"Зимнее яблоко":[48,45],
"Зимний огурец":[47,45],
"Зимняя вишня":[206,191],
"Зимняя маракуйя":[69,62],
"Зимняя мята":[112,100],
"Золотая маргарита":[411,371],
"Золотая осень":[50,45],
"Золотая слеза":[68,63],
"Золотая текила бум":[730,641],
"Золотая текила с лаймом и солью":[219,203],
"Золотое дно":[143,114],
"Золотой имбирный ром":[53,47],
"Зомби":[1023,918],
"Зомби 2":[177,166],
"Зыбучие пески":[66,61],
"Изабелла":[39,37],
"Изкарагуа":[82,81],
"Имбирная страсть":[107,104],
"Имбирно-виноградный мартини":[48,42],
"Имбирный виски":[157,143],
"Имбирный пряник":[67,59],
"Имбирный смэш":[58,50],
"Имбирный чейзер":[74,67],
"Индийский сауэр":[45,42],
"Инес":[68,61],
"Инкогнито":[57,55],
"Ирландские братья":[158,142],
"Ирландский имбирный эль":[163,142],
"Ирландский кофе":[547,506],
"Ирландский олд фешенд":[74,68],
"Ирландский пирог тодди":[116,106],
"Ирландский пьяный пунш":[73,66],
"Ирландский штрудель":[58,51],
"Ирония судьбы":[47,44],
"Исаев мартини":[160,145],
"Испанский эг-ног":[94,86],
"Истинная страсть":[63,59],
"Итальянский спритц пунш":[78,71],
"Кабальеро":[63,56],
"Кайпиринья":[843,755],
"Кайпиринья 2":[82,75],
"Кайпиринья ежевичная":[80,73],
"Кайпиринья клубничная":[80,72],
"Кайпироска":[489,436],
"Калигула":[82,76],
"Калина мартини":[49,44],
"Камикадзе в сифоне":[222,198],
"Камикадзе в шейкере":[233,213],
"Капри":[49,48],
"Кардикас":[52,47],
"Карел Готт":[176,165],
"Карибиан тач":[69,61],
"Карибский бриз":[99,92],
"Карибский кофе":[252,213],
"Карибское сокровище":[75,66],
"Карин":[38,33],
"Карловарская осень":[44,39],
"Карма":[64,60],
"Карнавальный физ":[69,63],
"Кассинни":[82,74],
"Квасной смузи":[73,69],
"Кейп Кодер":[607,504],
"Кембридж":[139,128],
"Кентукки кулер":[47,46],
"Кефирно-брусничный милкшейк":[42,38],
"Кефирно-вишневый милкшейк":[57,46],
"Кефирно-малиновый милкшейк":[128,114],
"Кефирно-облепиховый милкшейк":[79,68],
"Кефирно-фруктовый милкшейк":[95,73],
"Киви лимонад в кувшине":[102,91],
"Килим":[49,48],
"Кин-дза-дза":[117,105],
"Кир Рояль":[3564,3019],
"Клабленд":[46,44],
"Клавдий Гален":[84,79],
"Классический лимонад в кувшине":[288,246],
"Кленовое яблоко":[124,115],
"Кленовый джулеп":[64,58],
"Кловер клаб":[461,419],
"Кловер клаб 2":[55,52],
"Клуб Пегу":[42,40],
"Клубничный глинтвейн":[48,44],
"Клубничный коблер 317":[97,91],
"Клубничный лимонад":[221,199],
"Клубничный маларки":[112,96],
"Клубничный милкшейк":[726,634],
"Клубничный новогодний пунш":[56,51],
"Клубничный слинг":[123,113],
"Клюква краш":[85,73],
"Клюква с тимьяном":[42,37],
"Кокосовая клюква":[108,95],
"Кокосовая кола":[227,208],
"Кокосовая сангрия в кувшине":[51,45],
"Кокосовое яблоко":[89,77],
"Кокосовый ананас":[191,164],
"Кокосовый банан":[75,67],
"Кокосовый бриз":[148,136],
"Кокосовый бриз в кувшине":[71,56],
"Кокосовый лимонад в кувшине":[211,183],
"Кокосовый спрайт":[203,180],
"Кола и грейпфрутовый ликер":[85,68],
"Компот из детского сада в кувшине":[47,44],
"Компот из киви в кувшине":[87,78],
"Конка Д'Оро":[56,53],
"Конот мартини":[89,79],
"Контрольный выстрел":[220,195],
"Корица по-французски":[98,85],
"Королевский ревень":[88,78],
"Королевское искушение":[94,87],
"Королевское яблоко":[39,37],
"Короткий медовый месяц":[142,130],
"Космо ти":[63,54],
"Космополитен":[7420,6718],
"Космополитен желе":[41,38],
"Кофе коктейль":[69,65],
"Кранберини":[76,64],
"Красная Москва":[91,87],
"Красная площадь":[95,88],
"Красная сангрия в кувшине":[128,114],
"Красная сангрия в пунше":[66,63],
"Краснокожий мачо":[192,167],
"Красный":[57,53],
"Красный пес":[375,328],
"Красный сауэр":[131,118],
"Красный чай":[71,70],
"Крем де ля крем":[49,46],
"Крепкий глинтвейн":[100,94],
"Кржемилек и Вахмурка":[63,55],
"Кровавая Машка":[331,295],
"Кровавая Молли":[105,97],
"Кровавая Мэри":[6855,6220],
"Кровавая маленькая Маша":[170,156],
"Кровавый Джозеф":[283,251],
"Кровь и песок":[366,338],
"Куба либре":[2273,2088],
"Кузнечик":[601,531],
"Кукарача":[138,124],
"Кул свит харт":[111,107],
"Кумкват ти":[56,53],
"Курант биттер лемон":[41,36],
"Курант шот":[128,119],
"Куртизанка":[135,128],
"Кэнди шот":[80,72],
"Лав ми ду":[72,66],
"Лавандовый крем-брюле":[78,78],
"Лавина":[95,89],
"Лакомый кусочек":[50,45],
"Леди Скарлет":[121,110],
"Леди киллер":[191,177],
"Лейзи мэн флип":[40,35],
"Лексус":[565,493],
"Лена":[91,86],
"Летающий кузнечик":[194,185],
"Летний бриз":[72,66],
"Летний физ":[86,78],
"Летняя королева":[74,66],
"Ликер манго и апельсин":[64,59],
"Лимонад тархун в кувшине":[235,212],
"Лимонад тархун с облепихой в сифоне":[128,112],
"Липовый с тимьяном":[82,77],
"Лицо со шрамом":[129,120],
"Лолита":[87,80],
"Лонг айленд айс ти":[9084,8291],
"Лонг айленд во френч-прессе":[175,162],
"Лонг айленд пунш":[149,132],
"Лонг берри айс ти":[92,82],
"Лондонский мятный свизл":[134,124],
"Лошадиная шея":[145,132],
"Любимый":[51,49],
"Ма шери":[154,135],
"Мадам":[147,130],
"Мадам кофе":[134,114],
"Май тай":[3271,2975],
"Май тай 2":[274,254],
"Май тай 3":[244,211],
"Май тай 4":[203,186],
"Майорка":[51,48],
"Малевич шутер":[371,342],
"Маленькая соленая собака":[141,130],
"Маленький хаммер":[66,63],
"Маленький цветок":[144,134],
"Малиновая самбука":[113,108],
"Малиновое путешествие":[96,80],
"Малиновые амбиции":[86,82],
"Малиновый коблер 317":[65,60],
"Малиновый лимонад":[151,123],
"Малиновый лимонадик":[69,64],
"Малиновый милкшейк":[139,124],
"Малиновый сбитень":[135,119],
"Малиновый слинг":[109,100],
"Малиновый шот":[89,83],
"Манго дайкири":[86,78],
"Манго коблер 317":[96,93],
"Манго ром коллинз":[63,57],
"Манго слинг":[98,95],
"Манговый милкшейк с ряженкой":[39,36],
"Мандарин тини":[41,38],
"Мандарин шот":[227,212],
"Мандариновая дива":[149,129],
"Мандариновая маргарита":[45,37],
"Мандариновый лимонад":[92,88],
"Мандариновый лимонад в кувшине":[112,98],
"Мандариновый чай со смородиной":[39,33],
"Манки бизнес":[90,87],
"Манхэттен":[1809,1643],
"Мар дель плата":[46,42],
"Маргарита":[12041,10912],
"Маргарита без сахара":[316,289],
"Маргарита домашняя":[297,269],
"Маргарита домашняя 2":[48,45],
"Маргарита клубничная":[1069,960],
"Маргарита утренняя":[60,57],
"Марк Лициний Красс":[196,182],
"Марокканский смэш":[140,120],
"Мартинез":[524,474],
"Мартини Рояле":[1308,1206],
"Мартини мохитато":[334,299],
"Маска зла":[165,151],
"Мастер и Маргарита":[106,97],
"Матадор":[67,62],
"Медовая сосалка":[53,51],
"Медовый Версаль":[43,43],
"Медовый смэш":[39,37],
"Медуза":[353,317],
"Мей би хот":[39,39],
"Мексиканец":[88,82],
"Мексиканская радуга":[121,114],
"Мексиканский завтрак":[42,42],
"Мексиканский космонавт":[412,351],
"Мексиканский мул":[78,73],
"Мексиканский пирог":[47,43],
"Мексиканский поцелуй":[396,346],
"Мелоник":[196,182],
"Миксет":[61,57],
"Милано бриз":[202,172],
"Милано спритцер":[131,120],
"Милки вей":[182,173],
"Мимоза":[1149,998],
"Мисс Мартини":[68,63],
"Мицубиши":[187,168],
"Модный оргазм":[728,658],
"Мока чоколата яя":[313,268],
"Молоко и мед":[49,43],
"Молочный бренди пунш":[90,83],
"Молочный виски пунш":[93,87],
"Монако":[122,108],
"Монах":[158,140],
"Монпансье":[53,49],
"Морковно-грушевый фреш":[115,106],
"Морс мартини":[55,51],
"Морской бриз":[387,343],
"Морской коктейль":[410,361],
"Московские огни":[285,262],
"Московский весенний пунш":[121,110],
"Московский ласси":[43,37],
"Московский мул":[1169,1079],
"Мохито":[8530,7697],
"Мохито безалкогольный":[573,495],
"Мохито голубичный":[149,130],
"Мохито ежевичный":[79,74],
"Мохито клубничный":[465,411],
"Мохито королевский":[174,155],
"Мохито малиновый":[91,82],
"Мохито сангрия":[84,70],
"Мохито шейкерато":[63,57],
"Мул с корицей":[53,50],
"Мулен Руж":[75,69],
"Мульти смэш":[158,149],
"Мунлайт":[132,122],
"Мятное пиво":[113,97],
"Мятный джулеп":[631,563],
"Мятный лимонад":[122,107],
"Мятный лимонад в кувшине":[136,118],
"Мятный микс":[68,61],
"Мятный смузи":[271,236],
"Мятный чай с ромом":[170,152],
"Найтс":[65,60],
"Нано-Мохито":[105,97],
"Наоми":[85,78],
"Наша Мэри":[291,258],
"Небеса":[106,100],
"Невинный секс":[843,726],
"Негрони":[3579,3289],
"Негрони 2":[333,297],
"Негрони на районе":[114,104],
"Нежный чай":[49,47],
"Неземная любовь":[64,51],
"Нерон":[43,40],
"Никербокер":[220,199],
"Никербокер 2":[70,56],
"Новый Нью-Йорк":[41,40],
"Норманди смэш":[81,61],
"Нот ин ми":[67,64],
"Ночь в Тунисе":[48,48],
"Нью фешн":[83,76],
"Нью-Йоркер":[124,110],
"О де ви":[119,109],
"Обезьяньи мозги":[422,382],
"Облака":[1557,1376],
"Облепиховый глинтвейн":[66,61],
"Облепиховый гринго":[49,46],
"Облепиховый дайкири":[80,70],
"Облепиховый лимонад в кувшине":[100,88],
"Огуречно-базиличный лимонад в кувшине":[136,113],
"Огуречно-грушевый фреш":[133,121],
"Огуречный кулер":[58,57],
"Огуречный лимонад":[219,197],
"Огуречный тини":[121,111],
"Оксфордский пунш":[94,82],
"Олд фешенд":[595,528],
"Олд фешенд на цедре":[54,50],
"Олд фешенд с ромашкой":[44,39],
"Олдбой":[192,174],
"Оле":[141,132],
"Оранж биттер":[174,159],
"Оранжевое настроение":[129,121],
"Ост-Индийский Негрони":[71,66],
"Острая тропикана":[76,69],
"От Алисы":[225,199],
"Отвертка":[2397,2180],
"Отпуск на Ямайке":[75,72],
"Охотник":[81,68],
"Очарованный":[41,40],
"Падение миссионера":[164,147],
"Палома":[112,105],
"Палома лайт":[444,379],
"Папочка":[92,91],
"Пача Ибица":[99,91],
"Пача Монако":[65,58],
"Пача Монте-Карло":[56,40],
"Пача Москва":[41,40],
"Пача Нью-Йорк":[210,189],
"Пача Сан-Паулу":[104,98],
"Педро Манхэттен":[73,64],
"Педро пунш":[68,59],
"Пеликан":[331,304],
"Перевернутый абрикосовый кир":[38,33],
"Персик очарованный солнцем":[39,37],
"Персиковый виски сауэр":[85,80],
"Персиковый ликер и апельсин":[87,76],
"Персиковый ликер и клюква":[50,48],
"Перфект континиус":[114,103],
"Петрушка":[42,38],
"Пилот":[371,322],
"Пиммс №6":[50,46],
"Пинк флойд":[123,118],
"Пинья Колада":[5570,5030],
"Пинья Колада в ананасе":[169,149],
"Пинья Колада в кокосе":[121,112],
"Пинья Колада домашняя":[201,158],
"Пирамида шутер":[68,60],
"Пирсберри":[42,39],
"Писко пунш":[75,64],
"Писко сауэр":[266,247],
"Платиновая ягода":[48,44],
"Плиний Младший":[52,47],
"Под холодец":[156,141],
"Подарок из Амстердама":[133,118],
"Пожар в Техасе":[254,218],
"Полезный опыт":[59,54],
"Порнозвезда":[123,112],
"Последнее слово":[47,44],
"Пособие по безработице":[88,84],
"Потенциале спешл":[84,77],
"Поцелуй Дьявола":[121,112],
"Практически вишневый дайкири":[43,41],
"Примавера":[40,36],
"Прованс":[66,63],
"Противная слякоть":[517,432],
"Пряный грейпфрут":[54,53],
"Пряный ром с колой":[148,141],
"Птичий помет":[178,165],
"Пунш плантатора":[202,191],
"Путь вперед":[42,38],
"Пушкин тини":[83,73],
"Пчелка":[102,95],
"Пьяное золото":[40,39],
"Пэшн":[117,100],
"Пятый элемент":[181,164],
"Раздавленная лягушка":[194,169],
"Райский пунш":[103,79],
"Ракель":[195,175],
"Рамос джин физ":[345,313],
"Растафарай":[167,158],
"Рауль и Фидель":[68,55],
"Рафаэлло":[320,282],
"Реаниматор":[329,293],
"Ревеневый сауэр":[41,37],
"Ред базил смэш":[58,54],
"Ред дресс":[124,106],
"Ред хоуп":[71,68],
"Рейнгольд":[92,84],
"Реколл":[61,58],
"Ржавый гвоздь":[693,630],
"Ривер":[71,60],
"Роб Рой":[499,463],
"Роберта":[55,48],
"Розе вишня":[253,221],
"Розе клюква":[105,97],
"Розе с вишней":[122,110],
"Розе яблочный":[83,74],
"Розмари кулер":[57,51],
"Розмари кулер 2":[70,65],
"Розмари физ":[56,52],
"Розовый ром":[317,269],
"Рокфеллер шутер":[46,41],
"Роллинг слайс":[84,77],
"Ром золотой и ананас":[61,55],
"Ром кола":[1133,1041],
"Ром коллинз":[166,152],
"Ром круста свизл":[61,56],
"Ром мороженое":[280,248],
"Ром на вишне":[163,144],
"Ром с апельсиновым соком":[649,591],
"Ром с вишневым соком":[387,363],
"Ром с клюквенным морсом":[232,212],
"Ром с яблочным соком":[397,356],
"Ром со спрайтом":[479,425],
"Романтический дайкири":[53,50],
"Ромашковый лимонад в кувшине":[96,88],
"Ромовый пряный мусс":[57,46],
"Ромул":[75,71],
"Рори":[40,37],
"Россини":[403,364],
"Россо гранат":[194,166],
"Россо ягодный краш":[62,52],
"Роуз ли":[60,56],
"Роял дрим":[97,89],
"Роял лимонад":[139,128],
"Роял фламбе":[48,47],
"Роял флеш":[57,49],
"Роял шот":[200,187],
"Рубин":[96,85],
"Руди пэшн":[39,34],
"Русский лонг айленд":[210,198],
"Русский национальный":[63,60],
"Русско-японская война":[321,296],
"Рязанов":[43,41],
"С Фиделем":[97,88],
"Сазерак":[582,549],
"Сайдкар":[472,429],
"Самая быстрая кровавая Мэри":[72,70],
"Самбука":[1138,1011],
"Самоан фог каттер":[47,43],
"Сангрита":[995,924],
"Сангрита карлитос":[47,40],
"Сатисфекшн":[66,62],
"Сауэр 24":[103,92],
"Светофор":[334,306],
"Свирепый бык":[256,230],
"Свит харт":[71,61],
"Свит шот":[69,64],
"Северное сияние":[363,338],
"Севиче Мэри":[154,141],
"Севиче чейзер":[105,95],
"Сейдж романс":[121,99],
"Сейнт Пи":[41,39],
"Секс на пляже":[8842,7968],
"Секс на пляже лайт":[496,440],
"Секс на пляже спешл":[108,98],
"Секс с Анфисой":[72,69],
"Сеньорита":[63,57],
"Серебряная пуля":[450,398],
"Серебряная пуля (2)":[281,255],
"Серебряная пуля Соколова":[205,183],
"Серебряная текила с лаймом и солью":[170,154],
"Сингапурский слинг":[850,787],
"Сиреневый туман":[52,43],
"Сказка":[42,41],
"Скаффа":[60,56],
"Скитлс":[94,86],
"Скользкий сосок":[1309,1186],
"Сладенький":[139,120],
"Сладкие воспоминания":[127,117],
"Сладкий укус":[56,51],
"Сладко-яблочный драй":[228,208],
"Сливочная мечта":[84,75],
"Сливочный виски":[224,204],
"Смайл":[94,88],
"Смерть сверху":[66,61],
"Смородиновая кайпиринья":[125,102],
"Смородиновый космо":[69,61],
"Сникерс милкшейк":[709,633],
"Снусмумрик":[108,92],
"Собака ру":[873,746],
"Соблазнитель":[370,330],
"Содовая по-французски":[161,153],
"Содовая с имбирем":[71,66],
"Содовая с огурцом":[162,145],
"Соленая мучача":[90,84],
"Соленая собака":[423,359],
"Соленый русский":[79,73],
"Соленый русский шот":[55,52],
"Солнечная мечта":[61,58],
"Солнечный свет":[110,96],
"Солнце":[70,63],
"Солодовое золото":[48,46],
"Спайс энд айс":[50,48],
"Спрайт и яичный ликер":[92,85],
"Стайл мартини":[60,56],
"Стиль жизни":[84,77],
"Стингер":[222,202],
"Стратосфера":[270,239],
"Суббота":[63,54],
"Сука на пляже":[111,104],
"Счастливый билет":[47,43],
"Т-55":[557,486],
"Таежный сбитень":[41,36],
"Тамарита":[90,86],
"Таракан":[511,438],
"Тверская улица":[75,70],
"Творожно-ореховый милкшейк":[107,99],
"Твою мать":[338,308],
"Текила батанга":[456,406],
"Текила брусника апельсин":[76,72],
"Текила бум":[3478,3181],
"Текила вишня ананас":[80,74],
"Текила мадрас":[273,253],
"Текила мартини":[327,296],
"Текила санрайз":[5022,4427],
"Текила сауэр":[224,210],
"Текила смэш":[103,93],
"Текила спрайт":[509,471],
"Текила тореадор":[92,85],
"Текила яблоко брусника":[162,152],
"Темный ром с колой":[396,370],
"Теннесси кофе кап":[45,44],
"Тея":[99,93],
"Тиберий":[62,53],
"Тик так":[437,382],
"Тики маргарита":[52,49],
"Тирамису мартини":[112,103],
"Тихий огонь":[68,62],
"Тлеющий физ":[77,72],
"Тодди грог":[90,83],
"Том и Джерри":[108,100],
"Том коллинз":[1107,1018],
"Том ям мартини":[51,46],
"Томатный фреш с петрушкой":[141,121],
"Томми Ди сауэр":[141,127],
"Топ банана":[135,118],
"Топ биллинг":[160,139],
"Трава у моря":[106,94],
"Транссибирский экспресс":[170,156],
"Транссибирский экспресс горячий":[105,96],
"Трансформатор":[57,51],
"Тропическая маргарита":[90,86],
"Тропический лимонад в кувшине":[107,100],
"Тундра либре":[145,133],
"Туттоси":[60,51],
"Улыбка щавеля":[45,45],
"Ураган":[366,327],
"Ураган пунш":[78,71],
"Ураган шот":[376,324],
"Уральский лимонад":[83,76],
"Устрица прерий":[171,147],
"Устрица прерий (2)":[79,65],
"Устричный шутер":[76,71],
"Файнел кат":[45,44],
"Фантазия":[66,65],
"Фейхо наслаждение":[51,46],
"Ферри Корстен":[172,151],
"Феструс":[38,32],
"Фитнес смузи":[59,56],
"Флаг России":[1332,1155],
"Флирт маргарита":[88,77],
"Фокси леди шутер":[55,47],
"Форестер":[95,85],
"Форрест Гамп":[118,105],
"Форсаж":[202,179],
"Форум":[56,52],
"Фрамбуэза":[113,99],
"Французский гоголь-моголь":[63,60],
"Французский дайкири":[125,114],
"Французский кленовый чай":[46,43],
"Френч 75":[463,427],
"Френч 75 (2)":[97,84],
"Фруктовый блейзер":[93,87],
"Фруточино грейпфрутовый":[225,190],
"Фьюжн краш":[46,43],
"Халк":[276,236],
"Харви бол бенджер":[47,44],
"Хелп спешл флип":[38,37],
"Хелп эспрессо":[73,69],
"Хемингуэй дайкири":[333,310],
"Хиросима":[2093,1882],
"Хлеб да соль":[103,97],
"Холодный кофе аршат":[204,177],
"Храбрый бык":[557,491],
"Цвета осени":[45,42],
"Цветущий остров":[44,42],
"Цезарь":[68,62],
"Цитрон шот":[74,66],
"Цитрус джем":[47,43],
"Цитрусовая маргарита":[80,69],
"Цитрусовый Кейп Кодер":[53,46],
"Цицерон":[46,42],
"Цунами":[463,387],
"Чай доброе утро":[181,166],
"Чай цитрус с маракуйей":[64,56],
"Чайный мартини в 17 часов":[42,37],
"Чапурин":[170,153],
"Черная вишня":[148,136],
"Черное и белое":[199,155],
"Черносмородиновый":[127,107],
"Черносмородиновый лимонад в кувшине":[60,56],
"Черный октябрь":[90,85],
"Черный русский":[2011,1834],
"Черный флип":[123,111],
"Чешский глинтвейн":[119,99],
"Чешский сбитень":[62,61],
"Чивава":[272,256],
"Чиз крим":[42,41],
"Чики-пуки":[221,197],
"Чистая страсть":[99,94],
"Чувство":[63,59],
"Шампань коктейль":[121,109],
"Шампань фреш":[43,40],
"Шелест":[102,94],
"Шелковое сердце":[73,69],
"Шепот":[246,232],
"Шмель":[810,675],
"Шоколадно-апельсиновый мартини":[46,46],
"Шоколадно-мятная маргарита":[48,42],
"Шоколадный милкшейк":[375,332],
"Шоколадный чизкейк смузи":[94,86],
"Шоколадный эспрессо мартини":[77,70],
"Шот Павлова":[110,97],
"Шотландский олд фешенд":[79,72],
"Штырлиц":[212,192],
"Шум":[64,59],
"Щавелевый лимонад в кувшине":[72,66],
"Эволюция":[54,49],
"Эй-Би-Си":[281,239],
"Экзотический грог":[68,62],
"Экстра краш":[131,112],
"Элиза":[41,39],
"Эль Бандито":[365,339],
"Эль-Ниньо":[45,37],
"Энидей энивей шот":[51,49],
"Эспрессо мартини":[543,495],
"Эстетика":[47,45],
"Эффект бабочки":[112,99],
"Эффектини":[65,61],
"Южный дынный слинг":[60,59],
"Юниверсал":[149,138],
"Яблочная самбука":[39,36],
"Яблочно-апельсиновый фреш":[754,696],
"Яблочно-ванильный глинтвейн":[56,50],
"Яблочно-имбирная маргарита":[43,40],
"Яблочно-имбирный Мохито":[39,37],
"Яблочно-морковный фреш с имбирем":[214,205],
"Яблочно-сельдереевый фреш с имбирем":[345,315],
"Яблочное искушение":[57,52],
"Яблочное наслаждение":[245,210],
"Яблочный лимонад в кувшине":[85,76],
"Яблочный мармелад":[53,47],
"Яблочный мартини":[412,374],
"Яблочный пирог":[77,73],
"Яблочный ром кулер":[179,167],
"Яблочный сауэр":[106,93],
"Яблочный тини":[493,442],
"Ягодный дайкири смузи":[42,40],
"Ягодный лимонад":[145,122],
"Ягодный пиммс":[45,39],
"Ягодный твист":[80,67],
"Яичный милкшейк с ряженкой":[52,46],
"Ямайский мул":[103,91],
"Янки":[47,45],
"Японский космополитен":[199,181],
"Японский урожай":[50,49],
"№1":[180,154]
}